ivviewer/__init__.py
ivviewer/__main__.py
ivviewer/cursor.py
ivviewer/curve.py
ivviewer/ivcviewer.py
ivviewer/window.py
ivviewer/media/add_cursor.png
ivviewer/media/export.png
ivviewer/media/remove_all_cursors.png
ivviewer/media/remove_cursor.png
ivviewer/media/save_image.png
ivviewer/tests/__init__.py
ivviewer/tests/conftest.py
ivviewer/tests/test_cursor.py
ivviewer/tests/test_curve.py
ivviewer/tests/test_ivcviewer.py
ivviewer/tests/utils.py
ivviewer-1.0.1.dist-info/METADATA
ivviewer-1.0.1.dist-info/WHEEL
ivviewer-1.0.1.dist-info/entry_points.txt
ivviewer-1.0.1.dist-info/license_files/LICENSE
ivviewer-1.0.1.dist-info/RECORD
