Metadata-Version: 2.1
Name: ivviewer
Version: 1.0.1
Summary: A configurable Qt widget that displays IV curves
Author-email: EPC MSU <info@physlab.ru>
License: MIT License
Classifier: License :: OSI Approved :: MIT License
Classifier: Operating System :: OS Independent
Classifier: Programming Language :: Python :: 3
Requires-Python: <=3.8.10,>=3.6
Requires-Dist: dataclasses==0.8; python_version ~= '3.6.0'
Requires-Dist: numpy==1.18.1
Requires-Dist: pyqt5-sip>=12.0
Requires-Dist: pyqt5<=5.15.2,>=5.8.2
Requires-Dist: pythonqwt==0.8.3
